README.md
setup.cfg
setup.py
car_scraper/__init__.py
car_scraper/__main__.py
car_scraper/car_scraping_1.py
car_scraper_cc.egg-info/PKG-INFO
car_scraper_cc.egg-info/SOURCES.txt
car_scraper_cc.egg-info/dependency_links.txt
car_scraper_cc.egg-info/requires.txt
car_scraper_cc.egg-info/top_level.txt
rds_uploader/__init__.py
rds_uploader/rds_scraped_ebay_cars.py
test/__init__.py
test/test_car_scraping_1.py